{
  "metadata" : {
    "identifier" : "https://www.dtv-ebook.com/bien-co-mien-tay-hinh-bong-cu_19829.html",
    "title" : "Biển Cỏ Miền Tây - Hình Bóng Cũ",
    "subtitle" : "N/A",
    "author" : {
      "name" : "Sơn Nam",
      "sortAs" : ""
    },
    "narrator" : "N/A",
    "language" : "vi",
    "description" : "<p>N/A</p>",
    "publisher" : "N/A",
    "subject" : null,
    "modified" : null,
    "published" : "2023-09-06",
    "duration" : 5087,
    "abridged" : false,
    "conformsTo" : null,
    "numberOfPages" : null,
    "readingProgression" : null,
    "belongsTo" : null,
    "presentation" : null,
    "@type" : "http://schema.org/Audiobook",
    "schema:license" : "https://creativecommons.org/publicdomain/zero/1.0/"
  },
  "links" : [ {
    "rel" : "self",
    "href" : "https://raw.githubusercontent.com/duyhv/book_storage_three9/main/EPUB/EPUB_e5be3e8dd965fe1e35940cf18c1ccb50.json",
    "type" : "application/audiobook+json"
  }, {
    "rel" : "cover",
    "href" : "https://raw.githubusercontent.com/duyhv/book_storage_three9/main/IMAGE/IMAGE_e5be3e8dd965fe1e35940cf18c1ccb50.jpg",
    "type" : "image/jpeg",
    "height" : 300,
    "width" : 300
  } ],
  "readingOrder" : [ {
    "href" : "https://archive.org/download/may-troi/may-troi.mp3",
    "type" : "audio/mpeg",
    "bitrate" : 128,
    "duration" : 5087,
    "title" : "may-troi",
    "properties" : null,
    "alternate" : null
  } ],
  "toc" : [ {
    "href" : "https://archive.org/download/may-troi/may-troi.mp3",
    "title" : "may-troi",
    "children" : [ ]
  } ],
  "@context" : "https://readium.org/webpub-manifest/context.jsonld"
}