{
  "metadata" : {
    "identifier" : "https://www.nettruyenio.com/truyen-tranh/hayaku-shitai-futari-74309",
    "title" : "Hayaku Shitai Futari - Chapter 3",
    "subtitle" : null,
    "author" : null,
    "narrator" : null,
    "language" : "vi",
    "description" : null,
    "publisher" : "N/A",
    "subject" : null,
    "modified" : null,
    "published" : "2023-08-24",
    "duration" : 0,
    "abridged" : false,
    "conformsTo" : "https://readium.org/webpub-manifest/profiles/divina",
    "numberOfPages" : 74,
    "readingProgression" : "ttb",
    "belongsTo" : null,
    "presentation" : {
      "fit" : "width",
      "overflow" : "scrolled",
      "continuous" : true
    },
    "@type" : null,
    "schema:license" : null
  },
  "links" : [ {
    "rel" : "self",
    "href" : "https://raw.githubusercontent.com/thuvienonline40/book_storage_collection/main/comic_manifest.json",
    "type" : "application/divina+json"
  } ],
  "readingOrder" : [ {
    "href" : "https://raw.githubusercontent.com/tsvhcomic29/comic_storage9/main/IMAGE/IMAGE_8ef47cac2064e8e81725226dc006c965_1673c13aa8e9694c53fdc14938b76568_886c0fb3c9c239ae4966ffb5e73f5bac.jpg",
    "type" : "image/jpeg",
    "bitrate" : 0,
    "duration" : 0,
    "title" : null,
    "properties" : null,
    "alternate" : [ {
      "href" : "https://i221.ntcdntempv3.com/data/images/74309/928908/001-c5dca3d.jpg?data=net",
      "type" : "image/jpeg",
      "bitrate" : 0,
      "duration" : 0,
      "title" : null,
      "properties" : null,
      "alternate" : null
    } ]
  }, {
    "href" : "https://raw.githubusercontent.com/tsvhcomic29/comic_storage9/main/IMAGE/IMAGE_8ef47cac2064e8e81725226dc006c965_1673c13aa8e9694c53fdc14938b76568_6d309fd681892479b8af00a31ad9ac74.jpg",
    "type" : "image/jpeg",
    "bitrate" : 0,
    "duration" : 0,
    "title" : null,
    "properties" : null,
    "alternate" : [ {
      "href" : "https://i221.ntcdntempv3.com/data/images/74309/928908/002-99af122.jpg?data=net",
      "type" : "image/jpeg",
      "bitrate" : 0,
      "duration" : 0,
      "title" : null,
      "properties" : null,
      "alternate" : null
    } ]
  }, {
    "href" : "https://raw.githubusercontent.com/tsvhcomic29/comic_storage9/main/IMAGE/IMAGE_8ef47cac2064e8e81725226dc006c965_1673c13aa8e9694c53fdc14938b76568_af2a36f85d3b38a17202900e12ddc987.jpg",
    "type" : "image/jpeg",
    "bitrate" : 0,
    "duration" : 0,
    "title" : null,
    "properties" : null,
    "alternate" : [ {
      "href" : "https://i221.ntcdntempv3.com/data/images/74309/928908/003-880c1f5.jpg?data=net",
      "type" : "image/jpeg",
      "bitrate" : 0,
      "duration" : 0,
      "title" : null,
      "properties" : null,
      "alternate" : null
    } ]
  }, {
    "href" : "https://raw.githubusercontent.com/tsvhcomic29/comic_storage9/main/IMAGE/IMAGE_8ef47cac2064e8e81725226dc006c965_1673c13aa8e9694c53fdc14938b76568_96700419a469431b0aaae0692252dbf0.jpg",
    "type" : "image/jpeg",
    "bitrate" : 0,
    "duration" : 0,
    "title" : null,
    "properties" : null,
    "alternate" : [ {
      "href" : "https://i221.ntcdntempv3.com/data/images/74309/928908/004-56776d4.jpg?data=net",
      "type" : "image/jpeg",
      "bitrate" : 0,
      "duration" : 0,
      "title" : null,
      "properties" : null,
      "alternate" : null
    } ]
  }, {
    "href" : "https://raw.githubusercontent.com/tsvhcomic29/comic_storage9/main/IMAGE/IMAGE_8ef47cac2064e8e81725226dc006c965_1673c13aa8e9694c53fdc14938b76568_07ed96bb4f9266ab624f19007038f9a9.jpg",
    "type" : "image/jpeg",
    "bitrate" : 0,
    "duration" : 0,
    "title" : null,
    "properties" : null,
    "alternate" : [ {
      "href" : "https://i221.ntcdntempv3.com/data/images/74309/928908/005-eab2d41.jpg?data=net",
      "type" : "image/jpeg",
      "bitrate" : 0,
      "duration" : 0,
      "title" : null,
      "properties" : null,
      "alternate" : null
    } ]
  }, {
    "href" : "https://raw.githubusercontent.com/tsvhcomic29/comic_storage9/main/IMAGE/IMAGE_8ef47cac2064e8e81725226dc006c965_1673c13aa8e9694c53fdc14938b76568_70f09e5531f2cbdd88cc92a43a4d878b.jpg",
    "type" : "image/jpeg",
    "bitrate" : 0,
    "duration" : 0,
    "title" : null,
    "properties" : null,
    "alternate" : [ {
      "href" : "https://i221.ntcdntempv3.com/data/images/74309/928908/006-a46f9c8.jpg?data=net",
      "type" : "image/jpeg",
      "bitrate" : 0,
      "duration" : 0,
      "title" : null,
      "properties" : null,
      "alternate" : null
    } ]
  }, {
    "href" : "https://raw.githubusercontent.com/tsvhcomic29/comic_storage9/main/IMAGE/IMAGE_8ef47cac2064e8e81725226dc006c965_1673c13aa8e9694c53fdc14938b76568_d1b0361b6b2600dbf6e964d0b5c9c28b.jpg",
    "type" : "image/jpeg",
    "bitrate" : 0,
    "duration" : 0,
    "title" : null,
    "properties" : null,
    "alternate" : [ {
      "href" : "https://i221.ntcdntempv3.com/data/images/74309/928908/007-62e5ef8.jpg?data=net",
      "type" : "image/jpeg",
      "bitrate" : 0,
      "duration" : 0,
      "title" : null,
      "properties" : null,
      "alternate" : null
    } ]
  }, {
    "href" : "https://raw.githubusercontent.com/tsvhcomic29/comic_storage9/main/IMAGE/IMAGE_8ef47cac2064e8e81725226dc006c965_1673c13aa8e9694c53fdc14938b76568_a4a676849e2d08b51b908c7069e93e0a.jpg",
    "type" : "image/jpeg",
    "bitrate" : 0,
    "duration" : 0,
    "title" : null,
    "properties" : null,
    "alternate" : [ {
      "href" : "https://i221.ntcdntempv3.com/data/images/74309/928908/008-b37e023.jpg?data=net",
      "type" : "image/jpeg",
      "bitrate" : 0,
      "duration" : 0,
      "title" : null,
      "properties" : null,
      "alternate" : null
    } ]
  }, {
    "href" : "https://raw.githubusercontent.com/tsvhcomic29/comic_storage9/main/IMAGE/IMAGE_8ef47cac2064e8e81725226dc006c965_1673c13aa8e9694c53fdc14938b76568_845d125f1e60153e3178b2ac3aad7b63.jpg",
    "type" : "image/jpeg",
    "bitrate" : 0,
    "duration" : 0,
    "title" : null,
    "properties" : null,
    "alternate" : [ {
      "href" : "https://i221.ntcdntempv3.com/data/images/74309/928908/009-d60ad5c.jpg?data=net",
      "type" : "image/jpeg",
      "bitrate" : 0,
      "duration" : 0,
      "title" : null,
      "properties" : null,
      "alternate" : null
    } ]
  }, {
    "href" : "https://raw.githubusercontent.com/tsvhcomic29/comic_storage9/main/IMAGE/IMAGE_8ef47cac2064e8e81725226dc006c965_1673c13aa8e9694c53fdc14938b76568_89bb5d246eeb1e3bd90cb8f61ab1b652.jpg",
    "type" : "image/jpeg",
    "bitrate" : 0,
    "duration" : 0,
    "title" : null,
    "properties" : null,
    "alternate" : [ {
      "href" : "https://i221.ntcdntempv3.com/data/images/74309/928908/010-b9839db.jpg?data=net",
      "type" : "image/jpeg",
      "bitrate" : 0,
      "duration" : 0,
      "title" : null,
      "properties" : null,
      "alternate" : null
    } ]
  }, {
    "href" : "https://raw.githubusercontent.com/tsvhcomic29/comic_storage9/main/IMAGE/IMAGE_8ef47cac2064e8e81725226dc006c965_1673c13aa8e9694c53fdc14938b76568_b200ffcb0b7bba042bf5494436e881bf.jpg",
    "type" : "image/jpeg",
    "bitrate" : 0,
    "duration" : 0,
    "title" : null,
    "properties" : null,
    "alternate" : [ {
      "href" : "https://i221.ntcdntempv3.com/data/images/74309/928908/011-ed96590.jpg?data=net",
      "type" : "image/jpeg",
      "bitrate" : 0,
      "duration" : 0,
      "title" : null,
      "properties" : null,
      "alternate" : null
    } ]
  }, {
    "href" : "https://raw.githubusercontent.com/tsvhcomic29/comic_storage9/main/IMAGE/IMAGE_8ef47cac2064e8e81725226dc006c965_1673c13aa8e9694c53fdc14938b76568_6cc93dd50cdcc51c671d87ac5e6d7172.jpg",
    "type" : "image/jpeg",
    "bitrate" : 0,
    "duration" : 0,
    "title" : null,
    "properties" : null,
    "alternate" : [ {
      "href" : "https://i221.ntcdntempv3.com/data/images/74309/928908/012-4012e45.jpg?data=net",
      "type" : "image/jpeg",
      "bitrate" : 0,
      "duration" : 0,
      "title" : null,
      "properties" : null,
      "alternate" : null
    } ]
  }, {
    "href" : "https://raw.githubusercontent.com/tsvhcomic29/comic_storage9/main/IMAGE/IMAGE_8ef47cac2064e8e81725226dc006c965_1673c13aa8e9694c53fdc14938b76568_83ba69bd1d749926ca6a2d8cbdf24f77.jpg",
    "type" : "image/jpeg",
    "bitrate" : 0,
    "duration" : 0,
    "title" : null,
    "properties" : null,
    "alternate" : [ {
      "href" : "https://i221.ntcdntempv3.com/data/images/74309/928908/013-4192fb4.jpg?data=net",
      "type" : "image/jpeg",
      "bitrate" : 0,
      "duration" : 0,
      "title" : null,
      "properties" : null,
      "alternate" : null
    } ]
  }, {
    "href" : "https://raw.githubusercontent.com/tsvhcomic29/comic_storage9/main/IMAGE/IMAGE_8ef47cac2064e8e81725226dc006c965_1673c13aa8e9694c53fdc14938b76568_cad715f7c5bb68e7345311f6cb11820c.jpg",
    "type" : "image/jpeg",
    "bitrate" : 0,
    "duration" : 0,
    "title" : null,
    "properties" : null,
    "alternate" : [ {
      "href" : "https://i221.ntcdntempv3.com/data/images/74309/928908/014-902632e.jpg?data=net",
      "type" : "image/jpeg",
      "bitrate" : 0,
      "duration" : 0,
      "title" : null,
      "properties" : null,
      "alternate" : null
    } ]
  }, {
    "href" : "https://raw.githubusercontent.com/tsvhcomic29/comic_storage9/main/IMAGE/IMAGE_8ef47cac2064e8e81725226dc006c965_1673c13aa8e9694c53fdc14938b76568_626fb1cad5b4f70e96a89323038247fb.jpg",
    "type" : "image/jpeg",
    "bitrate" : 0,
    "duration" : 0,
    "title" : null,
    "properties" : null,
    "alternate" : [ {
      "href" : "https://i221.ntcdntempv3.com/data/images/74309/928908/015-f5d4ce8.jpg?data=net",
      "type" : "image/jpeg",
      "bitrate" : 0,
      "duration" : 0,
      "title" : null,
      "properties" : null,
      "alternate" : null
    } ]
  }, {
    "href" : "https://raw.githubusercontent.com/tsvhcomic29/comic_storage9/main/IMAGE/IMAGE_8ef47cac2064e8e81725226dc006c965_1673c13aa8e9694c53fdc14938b76568_4a8be2ab1993d49d90c9f55cf35ade46.jpg",
    "type" : "image/jpeg",
    "bitrate" : 0,
    "duration" : 0,
    "title" : null,
    "properties" : null,
    "alternate" : [ {
      "href" : "https://i221.ntcdntempv3.com/data/images/74309/928908/016-aace5ad.jpg?data=net",
      "type" : "image/jpeg",
      "bitrate" : 0,
      "duration" : 0,
      "title" : null,
      "properties" : null,
      "alternate" : null
    } ]
  }, {
    "href" : "https://raw.githubusercontent.com/tsvhcomic29/comic_storage9/main/IMAGE/IMAGE_8ef47cac2064e8e81725226dc006c965_1673c13aa8e9694c53fdc14938b76568_a9f3c3b13ec87f812a12e09462b8530d.jpg",
    "type" : "image/jpeg",
    "bitrate" : 0,
    "duration" : 0,
    "title" : null,
    "properties" : null,
    "alternate" : [ {
      "href" : "https://i221.ntcdntempv3.com/data/images/74309/928908/017-259c5dc.jpg?data=net",
      "type" : "image/jpeg",
      "bitrate" : 0,
      "duration" : 0,
      "title" : null,
      "properties" : null,
      "alternate" : null
    } ]
  }, {
    "href" : "https://raw.githubusercontent.com/tsvhcomic29/comic_storage9/main/IMAGE/IMAGE_8ef47cac2064e8e81725226dc006c965_1673c13aa8e9694c53fdc14938b76568_596bb0d41bc3bbebd0dc1370f8d3f154.jpg",
    "type" : "image/jpeg",
    "bitrate" : 0,
    "duration" : 0,
    "title" : null,
    "properties" : null,
    "alternate" : [ {
      "href" : "https://i221.ntcdntempv3.com/data/images/74309/928908/018-ceb26b9.jpg?data=net",
      "type" : "image/jpeg",
      "bitrate" : 0,
      "duration" : 0,
      "title" : null,
      "properties" : null,
      "alternate" : null
    } ]
  }, {
    "href" : "https://raw.githubusercontent.com/tsvhcomic29/comic_storage9/main/IMAGE/IMAGE_8ef47cac2064e8e81725226dc006c965_1673c13aa8e9694c53fdc14938b76568_fe58ae8f9baa311577d5f30a348bebc6.jpg",
    "type" : "image/jpeg",
    "bitrate" : 0,
    "duration" : 0,
    "title" : null,
    "properties" : null,
    "alternate" : [ {
      "href" : "https://i221.ntcdntempv3.com/data/images/74309/928908/019-afa5b48.jpg?data=net",
      "type" : "image/jpeg",
      "bitrate" : 0,
      "duration" : 0,
      "title" : null,
      "properties" : null,
      "alternate" : null
    } ]
  }, {
    "href" : "https://raw.githubusercontent.com/tsvhcomic29/comic_storage9/main/IMAGE/IMAGE_8ef47cac2064e8e81725226dc006c965_1673c13aa8e9694c53fdc14938b76568_9f178abb9ae3bd93304ef7ffa52e087a.jpg",
    "type" : "image/jpeg",
    "bitrate" : 0,
    "duration" : 0,
    "title" : null,
    "properties" : null,
    "alternate" : [ {
      "href" : "https://i221.ntcdntempv3.com/data/images/74309/928908/020-b6389f6.jpg?data=net",
      "type" : "image/jpeg",
      "bitrate" : 0,
      "duration" : 0,
      "title" : null,
      "properties" : null,
      "alternate" : null
    } ]
  }, {
    "href" : "https://raw.githubusercontent.com/tsvhcomic29/comic_storage9/main/IMAGE/IMAGE_8ef47cac2064e8e81725226dc006c965_1673c13aa8e9694c53fdc14938b76568_584c28af75dc4d7c6cd58e2892147b2d.jpg",
    "type" : "image/jpeg",
    "bitrate" : 0,
    "duration" : 0,
    "title" : null,
    "properties" : null,
    "alternate" : [ {
      "href" : "https://i221.ntcdntempv3.com/data/images/74309/928908/021-36cfe23.jpg?data=net",
      "type" : "image/jpeg",
      "bitrate" : 0,
      "duration" : 0,
      "title" : null,
      "properties" : null,
      "alternate" : null
    } ]
  }, {
    "href" : "https://raw.githubusercontent.com/tsvhcomic29/comic_storage9/main/IMAGE/IMAGE_8ef47cac2064e8e81725226dc006c965_1673c13aa8e9694c53fdc14938b76568_e56790b8bb6f0002af006cc69e1c3721.jpg",
    "type" : "image/jpeg",
    "bitrate" : 0,
    "duration" : 0,
    "title" : null,
    "properties" : null,
    "alternate" : [ {
      "href" : "https://i221.ntcdntempv3.com/data/images/74309/928908/022-3a2008c.jpg?data=net",
      "type" : "image/jpeg",
      "bitrate" : 0,
      "duration" : 0,
      "title" : null,
      "properties" : null,
      "alternate" : null
    } ]
  }, {
    "href" : "https://raw.githubusercontent.com/tsvhcomic29/comic_storage9/main/IMAGE/IMAGE_8ef47cac2064e8e81725226dc006c965_1673c13aa8e9694c53fdc14938b76568_aae9d72fee19b1e00234765c7b3c692a.jpg",
    "type" : "image/jpeg",
    "bitrate" : 0,
    "duration" : 0,
    "title" : null,
    "properties" : null,
    "alternate" : [ {
      "href" : "https://i221.ntcdntempv3.com/data/images/74309/928908/023-cf6f6df.jpg?data=net",
      "type" : "image/jpeg",
      "bitrate" : 0,
      "duration" : 0,
      "title" : null,
      "properties" : null,
      "alternate" : null
    } ]
  }, {
    "href" : "https://raw.githubusercontent.com/tsvhcomic29/comic_storage9/main/IMAGE/IMAGE_8ef47cac2064e8e81725226dc006c965_1673c13aa8e9694c53fdc14938b76568_af3e775507fe2e29f1748923863f600c.jpg",
    "type" : "image/jpeg",
    "bitrate" : 0,
    "duration" : 0,
    "title" : null,
    "properties" : null,
    "alternate" : [ {
      "href" : "https://i221.ntcdntempv3.com/data/images/74309/928908/024-be8726b.jpg?data=net",
      "type" : "image/jpeg",
      "bitrate" : 0,
      "duration" : 0,
      "title" : null,
      "properties" : null,
      "alternate" : null
    } ]
  }, {
    "href" : "https://raw.githubusercontent.com/tsvhcomic29/comic_storage9/main/IMAGE/IMAGE_8ef47cac2064e8e81725226dc006c965_1673c13aa8e9694c53fdc14938b76568_a01c5e5d0f43267238c76b53ddb109c9.jpg",
    "type" : "image/jpeg",
    "bitrate" : 0,
    "duration" : 0,
    "title" : null,
    "properties" : null,
    "alternate" : [ {
      "href" : "https://i221.ntcdntempv3.com/data/images/74309/928908/025-5ac307c.jpg?data=net",
      "type" : "image/jpeg",
      "bitrate" : 0,
      "duration" : 0,
      "title" : null,
      "properties" : null,
      "alternate" : null
    } ]
  }, {
    "href" : "https://raw.githubusercontent.com/tsvhcomic29/comic_storage9/main/IMAGE/IMAGE_8ef47cac2064e8e81725226dc006c965_1673c13aa8e9694c53fdc14938b76568_247e44a656f06b879e3ea02728e08838.jpg",
    "type" : "image/jpeg",
    "bitrate" : 0,
    "duration" : 0,
    "title" : null,
    "properties" : null,
    "alternate" : [ {
      "href" : "https://i221.ntcdntempv3.com/data/images/74309/928908/026-de30055.jpg?data=net",
      "type" : "image/jpeg",
      "bitrate" : 0,
      "duration" : 0,
      "title" : null,
      "properties" : null,
      "alternate" : null
    } ]
  }, {
    "href" : "https://raw.githubusercontent.com/tsvhcomic29/comic_storage9/main/IMAGE/IMAGE_8ef47cac2064e8e81725226dc006c965_1673c13aa8e9694c53fdc14938b76568_01dcecfe93b9b9af2963a4c6772a369e.jpg",
    "type" : "image/jpeg",
    "bitrate" : 0,
    "duration" : 0,
    "title" : null,
    "properties" : null,
    "alternate" : [ {
      "href" : "https://i221.ntcdntempv3.com/data/images/74309/928908/027-43a5160.jpg?data=net",
      "type" : "image/jpeg",
      "bitrate" : 0,
      "duration" : 0,
      "title" : null,
      "properties" : null,
      "alternate" : null
    } ]
  } ],
  "toc" : null,
  "@context" : "https://readium.org/webpub-manifest/context.jsonld"
}