{
  "metadata" : {
    "identifier" : "https://www.nettruyenio.com/truyen-tranh/chi-no-wadachi-159700",
    "title" : "Chi no Wadachi - Chapter 10",
    "subtitle" : null,
    "author" : null,
    "narrator" : null,
    "language" : "vi",
    "description" : null,
    "publisher" : "N/A",
    "subject" : null,
    "modified" : null,
    "published" : "2023-08-06",
    "duration" : 0,
    "abridged" : false,
    "conformsTo" : "https://readium.org/webpub-manifest/profiles/divina",
    "numberOfPages" : 116,
    "readingProgression" : "ttb",
    "belongsTo" : null,
    "presentation" : {
      "fit" : "width",
      "overflow" : "scrolled",
      "continuous" : true
    },
    "@type" : null,
    "schema:license" : null
  },
  "links" : [ {
    "rel" : "self",
    "href" : "https://raw.githubusercontent.com/thuvienonline40/book_storage_collection/main/comic_manifest.json",
    "type" : "application/divina+json"
  } ],
  "readingOrder" : [ {
    "href" : "https://raw.githubusercontent.com/quetcccd/comic_storage9/main/IMAGE/IMAGE_7d7bdd80160ebabc188c6376b1d7bc18_673b95eb37857ad23df0b09d8a2112fc_50970db98e0a3f4206844373978fb3bb.jpg",
    "type" : "image/jpeg",
    "bitrate" : 0,
    "duration" : 0,
    "title" : null,
    "properties" : null,
    "alternate" : [ {
      "href" : "https://i441.ntcdntempv26.com/data/images/15970/341491/001.jpg?data=net",
      "type" : "image/jpeg",
      "bitrate" : 0,
      "duration" : 0,
      "title" : null,
      "properties" : null,
      "alternate" : null
    } ]
  }, {
    "href" : "https://raw.githubusercontent.com/quetcccd/comic_storage9/main/IMAGE/IMAGE_7d7bdd80160ebabc188c6376b1d7bc18_673b95eb37857ad23df0b09d8a2112fc_cf9dcb8806b4bf00a21b131d69fff432.jpg",
    "type" : "image/jpeg",
    "bitrate" : 0,
    "duration" : 0,
    "title" : null,
    "properties" : null,
    "alternate" : [ {
      "href" : "https://i441.ntcdntempv26.com/data/images/15970/341491/002.jpg?data=net",
      "type" : "image/jpeg",
      "bitrate" : 0,
      "duration" : 0,
      "title" : null,
      "properties" : null,
      "alternate" : null
    } ]
  }, {
    "href" : "https://raw.githubusercontent.com/quetcccd/comic_storage9/main/IMAGE/IMAGE_7d7bdd80160ebabc188c6376b1d7bc18_673b95eb37857ad23df0b09d8a2112fc_74f42c1e2ebef601cfc2bbdeb264714a.jpg",
    "type" : "image/jpeg",
    "bitrate" : 0,
    "duration" : 0,
    "title" : null,
    "properties" : null,
    "alternate" : [ {
      "href" : "https://i441.ntcdntempv26.com/data/images/15970/341491/003.jpg?data=net",
      "type" : "image/jpeg",
      "bitrate" : 0,
      "duration" : 0,
      "title" : null,
      "properties" : null,
      "alternate" : null
    } ]
  }, {
    "href" : "https://raw.githubusercontent.com/quetcccd/comic_storage9/main/IMAGE/IMAGE_7d7bdd80160ebabc188c6376b1d7bc18_673b95eb37857ad23df0b09d8a2112fc_87ccb5f274727a6e76351ded5fdbef81.jpg",
    "type" : "image/jpeg",
    "bitrate" : 0,
    "duration" : 0,
    "title" : null,
    "properties" : null,
    "alternate" : [ {
      "href" : "https://i441.ntcdntempv26.com/data/images/15970/341491/004.jpg?data=net",
      "type" : "image/jpeg",
      "bitrate" : 0,
      "duration" : 0,
      "title" : null,
      "properties" : null,
      "alternate" : null
    } ]
  }, {
    "href" : "https://raw.githubusercontent.com/quetcccd/comic_storage9/main/IMAGE/IMAGE_7d7bdd80160ebabc188c6376b1d7bc18_673b95eb37857ad23df0b09d8a2112fc_1226fa852bff953122080a9765d110d2.jpg",
    "type" : "image/jpeg",
    "bitrate" : 0,
    "duration" : 0,
    "title" : null,
    "properties" : null,
    "alternate" : [ {
      "href" : "https://i441.ntcdntempv26.com/data/images/15970/341491/005.jpg?data=net",
      "type" : "image/jpeg",
      "bitrate" : 0,
      "duration" : 0,
      "title" : null,
      "properties" : null,
      "alternate" : null
    } ]
  }, {
    "href" : "https://raw.githubusercontent.com/quetcccd/comic_storage9/main/IMAGE/IMAGE_7d7bdd80160ebabc188c6376b1d7bc18_673b95eb37857ad23df0b09d8a2112fc_a0898a972fedfa5fca0396d995e046f5.jpg",
    "type" : "image/jpeg",
    "bitrate" : 0,
    "duration" : 0,
    "title" : null,
    "properties" : null,
    "alternate" : [ {
      "href" : "https://i441.ntcdntempv26.com/data/images/15970/341491/006.jpg?data=net",
      "type" : "image/jpeg",
      "bitrate" : 0,
      "duration" : 0,
      "title" : null,
      "properties" : null,
      "alternate" : null
    } ]
  }, {
    "href" : "https://raw.githubusercontent.com/quetcccd/comic_storage9/main/IMAGE/IMAGE_7d7bdd80160ebabc188c6376b1d7bc18_673b95eb37857ad23df0b09d8a2112fc_14de7571284c8e558d9493d9d71a28df.jpg",
    "type" : "image/jpeg",
    "bitrate" : 0,
    "duration" : 0,
    "title" : null,
    "properties" : null,
    "alternate" : [ {
      "href" : "https://i441.ntcdntempv26.com/data/images/15970/341491/007.jpg?data=net",
      "type" : "image/jpeg",
      "bitrate" : 0,
      "duration" : 0,
      "title" : null,
      "properties" : null,
      "alternate" : null
    } ]
  }, {
    "href" : "https://raw.githubusercontent.com/quetcccd/comic_storage9/main/IMAGE/IMAGE_7d7bdd80160ebabc188c6376b1d7bc18_673b95eb37857ad23df0b09d8a2112fc_037efa487bcda3a4b2e21300c3d73c27.jpg",
    "type" : "image/jpeg",
    "bitrate" : 0,
    "duration" : 0,
    "title" : null,
    "properties" : null,
    "alternate" : [ {
      "href" : "https://i441.ntcdntempv26.com/data/images/15970/341491/008.jpg?data=net",
      "type" : "image/jpeg",
      "bitrate" : 0,
      "duration" : 0,
      "title" : null,
      "properties" : null,
      "alternate" : null
    } ]
  }, {
    "href" : "https://raw.githubusercontent.com/quetcccd/comic_storage9/main/IMAGE/IMAGE_7d7bdd80160ebabc188c6376b1d7bc18_673b95eb37857ad23df0b09d8a2112fc_52c229f4060be26958d0161c120136ac.jpg",
    "type" : "image/jpeg",
    "bitrate" : 0,
    "duration" : 0,
    "title" : null,
    "properties" : null,
    "alternate" : [ {
      "href" : "https://i441.ntcdntempv26.com/data/images/15970/341491/009.jpg?data=net",
      "type" : "image/jpeg",
      "bitrate" : 0,
      "duration" : 0,
      "title" : null,
      "properties" : null,
      "alternate" : null
    } ]
  }, {
    "href" : "https://raw.githubusercontent.com/quetcccd/comic_storage9/main/IMAGE/IMAGE_7d7bdd80160ebabc188c6376b1d7bc18_673b95eb37857ad23df0b09d8a2112fc_3e7b03e21d334734e1ac596001ea2e45.jpg",
    "type" : "image/jpeg",
    "bitrate" : 0,
    "duration" : 0,
    "title" : null,
    "properties" : null,
    "alternate" : [ {
      "href" : "https://i441.ntcdntempv26.com/data/images/15970/341491/010.jpg?data=net",
      "type" : "image/jpeg",
      "bitrate" : 0,
      "duration" : 0,
      "title" : null,
      "properties" : null,
      "alternate" : null
    } ]
  }, {
    "href" : "https://raw.githubusercontent.com/quetcccd/comic_storage9/main/IMAGE/IMAGE_7d7bdd80160ebabc188c6376b1d7bc18_673b95eb37857ad23df0b09d8a2112fc_d8d2a6a396593e23d9aa1908b009bdcd.jpg",
    "type" : "image/jpeg",
    "bitrate" : 0,
    "duration" : 0,
    "title" : null,
    "properties" : null,
    "alternate" : [ {
      "href" : "https://i441.ntcdntempv26.com/data/images/15970/341491/011.jpg?data=net",
      "type" : "image/jpeg",
      "bitrate" : 0,
      "duration" : 0,
      "title" : null,
      "properties" : null,
      "alternate" : null
    } ]
  }, {
    "href" : "https://raw.githubusercontent.com/quetcccd/comic_storage9/main/IMAGE/IMAGE_7d7bdd80160ebabc188c6376b1d7bc18_673b95eb37857ad23df0b09d8a2112fc_651ea82e2bd7d36b8d77757a3df57c15.jpg",
    "type" : "image/jpeg",
    "bitrate" : 0,
    "duration" : 0,
    "title" : null,
    "properties" : null,
    "alternate" : [ {
      "href" : "https://i441.ntcdntempv26.com/data/images/15970/341491/012.jpg?data=net",
      "type" : "image/jpeg",
      "bitrate" : 0,
      "duration" : 0,
      "title" : null,
      "properties" : null,
      "alternate" : null
    } ]
  }, {
    "href" : "https://raw.githubusercontent.com/quetcccd/comic_storage9/main/IMAGE/IMAGE_7d7bdd80160ebabc188c6376b1d7bc18_673b95eb37857ad23df0b09d8a2112fc_b9f0783d781b3bff44a8614b14eb1e27.jpg",
    "type" : "image/jpeg",
    "bitrate" : 0,
    "duration" : 0,
    "title" : null,
    "properties" : null,
    "alternate" : [ {
      "href" : "https://i441.ntcdntempv26.com/data/images/15970/341491/013.jpg?data=net",
      "type" : "image/jpeg",
      "bitrate" : 0,
      "duration" : 0,
      "title" : null,
      "properties" : null,
      "alternate" : null
    } ]
  }, {
    "href" : "https://raw.githubusercontent.com/quetcccd/comic_storage9/main/IMAGE/IMAGE_7d7bdd80160ebabc188c6376b1d7bc18_673b95eb37857ad23df0b09d8a2112fc_36af58ff4da2673a9c194972abbd69d6.jpg",
    "type" : "image/jpeg",
    "bitrate" : 0,
    "duration" : 0,
    "title" : null,
    "properties" : null,
    "alternate" : [ {
      "href" : "https://i441.ntcdntempv26.com/data/images/15970/341491/014.jpg?data=net",
      "type" : "image/jpeg",
      "bitrate" : 0,
      "duration" : 0,
      "title" : null,
      "properties" : null,
      "alternate" : null
    } ]
  }, {
    "href" : "https://raw.githubusercontent.com/quetcccd/comic_storage9/main/IMAGE/IMAGE_7d7bdd80160ebabc188c6376b1d7bc18_673b95eb37857ad23df0b09d8a2112fc_1ae46d07e72a01deb341997438e4a6a1.jpg",
    "type" : "image/jpeg",
    "bitrate" : 0,
    "duration" : 0,
    "title" : null,
    "properties" : null,
    "alternate" : [ {
      "href" : "https://i441.ntcdntempv26.com/data/images/15970/341491/015.jpg?data=net",
      "type" : "image/jpeg",
      "bitrate" : 0,
      "duration" : 0,
      "title" : null,
      "properties" : null,
      "alternate" : null
    } ]
  }, {
    "href" : "https://raw.githubusercontent.com/quetcccd/comic_storage9/main/IMAGE/IMAGE_7d7bdd80160ebabc188c6376b1d7bc18_673b95eb37857ad23df0b09d8a2112fc_6235eba84d3cf3382c629ba5ec3238cc.jpg",
    "type" : "image/jpeg",
    "bitrate" : 0,
    "duration" : 0,
    "title" : null,
    "properties" : null,
    "alternate" : [ {
      "href" : "https://i441.ntcdntempv26.com/data/images/15970/341491/016.jpg?data=net",
      "type" : "image/jpeg",
      "bitrate" : 0,
      "duration" : 0,
      "title" : null,
      "properties" : null,
      "alternate" : null
    } ]
  }, {
    "href" : "https://raw.githubusercontent.com/quetcccd/comic_storage9/main/IMAGE/IMAGE_7d7bdd80160ebabc188c6376b1d7bc18_673b95eb37857ad23df0b09d8a2112fc_7af4f577daa1ecc345212fc8317b258a.jpg",
    "type" : "image/jpeg",
    "bitrate" : 0,
    "duration" : 0,
    "title" : null,
    "properties" : null,
    "alternate" : [ {
      "href" : "https://i441.ntcdntempv26.com/data/images/15970/341491/017.jpg?data=net",
      "type" : "image/jpeg",
      "bitrate" : 0,
      "duration" : 0,
      "title" : null,
      "properties" : null,
      "alternate" : null
    } ]
  }, {
    "href" : "https://raw.githubusercontent.com/quetcccd/comic_storage9/main/IMAGE/IMAGE_7d7bdd80160ebabc188c6376b1d7bc18_673b95eb37857ad23df0b09d8a2112fc_b2bec800cd38c8ccaae442cd05d095ef.jpg",
    "type" : "image/jpeg",
    "bitrate" : 0,
    "duration" : 0,
    "title" : null,
    "properties" : null,
    "alternate" : [ {
      "href" : "https://i441.ntcdntempv26.com/data/images/15970/341491/018.jpg?data=net",
      "type" : "image/jpeg",
      "bitrate" : 0,
      "duration" : 0,
      "title" : null,
      "properties" : null,
      "alternate" : null
    } ]
  }, {
    "href" : "https://raw.githubusercontent.com/quetcccd/comic_storage9/main/IMAGE/IMAGE_7d7bdd80160ebabc188c6376b1d7bc18_673b95eb37857ad23df0b09d8a2112fc_e9a4a9436ad57d71c2ef1736edfab3d3.jpg",
    "type" : "image/jpeg",
    "bitrate" : 0,
    "duration" : 0,
    "title" : null,
    "properties" : null,
    "alternate" : [ {
      "href" : "https://i441.ntcdntempv26.com/data/images/15970/341491/019.jpg?data=net",
      "type" : "image/jpeg",
      "bitrate" : 0,
      "duration" : 0,
      "title" : null,
      "properties" : null,
      "alternate" : null
    } ]
  }, {
    "href" : "https://raw.githubusercontent.com/quetcccd/comic_storage9/main/IMAGE/IMAGE_7d7bdd80160ebabc188c6376b1d7bc18_673b95eb37857ad23df0b09d8a2112fc_993de5f39495f97012635e099bd06932.jpg",
    "type" : "image/jpeg",
    "bitrate" : 0,
    "duration" : 0,
    "title" : null,
    "properties" : null,
    "alternate" : [ {
      "href" : "https://i441.ntcdntempv26.com/data/images/15970/341491/020.jpg?data=net",
      "type" : "image/jpeg",
      "bitrate" : 0,
      "duration" : 0,
      "title" : null,
      "properties" : null,
      "alternate" : null
    } ]
  }, {
    "href" : "https://raw.githubusercontent.com/quetcccd/comic_storage9/main/IMAGE/IMAGE_7d7bdd80160ebabc188c6376b1d7bc18_673b95eb37857ad23df0b09d8a2112fc_daca2dac9e22642d0616dba2aba731ca.jpg",
    "type" : "image/jpeg",
    "bitrate" : 0,
    "duration" : 0,
    "title" : null,
    "properties" : null,
    "alternate" : [ {
      "href" : "https://i441.ntcdntempv26.com/data/images/15970/341491/021.jpg?data=net",
      "type" : "image/jpeg",
      "bitrate" : 0,
      "duration" : 0,
      "title" : null,
      "properties" : null,
      "alternate" : null
    } ]
  }, {
    "href" : "https://raw.githubusercontent.com/quetcccd/comic_storage9/main/IMAGE/IMAGE_7d7bdd80160ebabc188c6376b1d7bc18_673b95eb37857ad23df0b09d8a2112fc_c084508649b86cbbd24e42aaac1ab400.jpg",
    "type" : "image/jpeg",
    "bitrate" : 0,
    "duration" : 0,
    "title" : null,
    "properties" : null,
    "alternate" : [ {
      "href" : "https://i441.ntcdntempv26.com/data/images/15970/341491/022.jpg?data=net",
      "type" : "image/jpeg",
      "bitrate" : 0,
      "duration" : 0,
      "title" : null,
      "properties" : null,
      "alternate" : null
    } ]
  }, {
    "href" : "https://raw.githubusercontent.com/quetcccd/comic_storage9/main/IMAGE/IMAGE_7d7bdd80160ebabc188c6376b1d7bc18_673b95eb37857ad23df0b09d8a2112fc_906d374d7ba56ac9b18580be6063c8ed.jpg",
    "type" : "image/jpeg",
    "bitrate" : 0,
    "duration" : 0,
    "title" : null,
    "properties" : null,
    "alternate" : [ {
      "href" : "https://i441.ntcdntempv26.com/data/images/15970/341491/023.jpg?data=net",
      "type" : "image/jpeg",
      "bitrate" : 0,
      "duration" : 0,
      "title" : null,
      "properties" : null,
      "alternate" : null
    } ]
  }, {
    "href" : "https://raw.githubusercontent.com/quetcccd/comic_storage9/main/IMAGE/IMAGE_7d7bdd80160ebabc188c6376b1d7bc18_673b95eb37857ad23df0b09d8a2112fc_afaeb7245af6232282e5856d3fd5ae9c.jpg",
    "type" : "image/jpeg",
    "bitrate" : 0,
    "duration" : 0,
    "title" : null,
    "properties" : null,
    "alternate" : [ {
      "href" : "https://i441.ntcdntempv26.com/data/images/15970/341491/024.jpg?data=net",
      "type" : "image/jpeg",
      "bitrate" : 0,
      "duration" : 0,
      "title" : null,
      "properties" : null,
      "alternate" : null
    } ]
  } ],
  "toc" : null,
  "@context" : "https://readium.org/webpub-manifest/context.jsonld"
}