{
  "metadata" : {
    "identifier" : "https://www.dtv-ebook.com/phat-hoc-pho-thong_12932.html",
    "title" : "Phật Học Phổ Thông",
    "subtitle" : "N/A",
    "author" : {
      "name" : "Thích Thiện Hoa",
      "sortAs" : ""
    },
    "narrator" : "N/A",
    "language" : "vi",
    "description" : "<p>N/A</p>",
    "publisher" : "N/A",
    "subject" : null,
    "modified" : null,
    "published" : "2024-04-29",
    "duration" : 186973,
    "abridged" : false,
    "conformsTo" : null,
    "numberOfPages" : null,
    "readingProgression" : null,
    "belongsTo" : null,
    "presentation" : null,
    "@type" : "http://schema.org/Audiobook",
    "schema:license" : "https://creativecommons.org/publicdomain/zero/1.0/"
  },
  "links" : [ {
    "rel" : "self",
    "href" : "https://raw.githubusercontent.com/duyhv/book_storage_three9/main/EPUB/EPUB_d1c90dd56880eae608b15d7c022697f1.json",
    "type" : "application/audiobook+json"
  }, {
    "rel" : "cover",
    "href" : "https://raw.githubusercontent.com/duyhv/book_storage_three9/main/IMAGE/IMAGE_d1c90dd56880eae608b15d7c022697f1.jpg",
    "type" : "image/jpeg",
    "height" : 300,
    "width" : 300
  } ],
  "readingOrder" : [ {
    "href" : "https://archive.org/download/d1c90dd56880eae608b15d7c022697f1/phan-1-trung-tam-dieu-phap-am-dieuphapam-net.mp3",
    "type" : "audio/mpeg",
    "bitrate" : 128,
    "duration" : 31735,
    "title" : "Phần 1 - Trung Tâm Diệu Pháp Âm - DieuPhapAm.Net",
    "properties" : null,
    "alternate" : null
  }, {
    "href" : "https://archive.org/download/d1c90dd56880eae608b15d7c022697f1/phan-2-trung-tam-dieu-phap-am-dieuphapam-net.mp3",
    "type" : "audio/mpeg",
    "bitrate" : 128,
    "duration" : 31585,
    "title" : "Phần 2 - Trung Tâm Diệu Pháp Âm - DieuPhapAm.Net",
    "properties" : null,
    "alternate" : null
  }, {
    "href" : "https://archive.org/download/d1c90dd56880eae608b15d7c022697f1/phan-3-trung-tam-dieu-phap-am-dieuphapam-net.mp3",
    "type" : "audio/mpeg",
    "bitrate" : 128,
    "duration" : 32207,
    "title" : "Phần 3 - Trung Tâm Diệu Pháp Âm - DieuPhapAm.Net",
    "properties" : null,
    "alternate" : null
  }, {
    "href" : "https://archive.org/download/d1c90dd56880eae608b15d7c022697f1/phan-4-trung-tam-dieu-phap-am-dieuphapam-net.mp3",
    "type" : "audio/mpeg",
    "bitrate" : 128,
    "duration" : 30628,
    "title" : "Phần 4 - Trung Tâm Diệu Pháp Âm - DieuPhapAm.Net",
    "properties" : null,
    "alternate" : null
  }, {
    "href" : "https://archive.org/download/d1c90dd56880eae608b15d7c022697f1/phan-5-trung-tam-dieu-phap-am-dieuphapam-net.mp3",
    "type" : "audio/mpeg",
    "bitrate" : 128,
    "duration" : 32091,
    "title" : "Phần 5 - Trung Tâm Diệu Pháp Âm - DieuPhapAm.Net",
    "properties" : null,
    "alternate" : null
  }, {
    "href" : "https://archive.org/download/d1c90dd56880eae608b15d7c022697f1/phan-6-trung-tam-dieu-phap-am-dieuphapam-net.mp3",
    "type" : "audio/mpeg",
    "bitrate" : 128,
    "duration" : 28727,
    "title" : "Phần 6 - Trung Tâm Diệu Pháp Âm - DieuPhapAm.Net",
    "properties" : null,
    "alternate" : null
  } ],
  "toc" : [ {
    "href" : "https://archive.org/download/d1c90dd56880eae608b15d7c022697f1/phan-1-trung-tam-dieu-phap-am-dieuphapam-net.mp3",
    "title" : "Phần 1 - Trung Tâm Diệu Pháp Âm - DieuPhapAm.Net",
    "children" : [ ]
  }, {
    "href" : "https://archive.org/download/d1c90dd56880eae608b15d7c022697f1/phan-2-trung-tam-dieu-phap-am-dieuphapam-net.mp3",
    "title" : "Phần 2 - Trung Tâm Diệu Pháp Âm - DieuPhapAm.Net",
    "children" : [ ]
  }, {
    "href" : "https://archive.org/download/d1c90dd56880eae608b15d7c022697f1/phan-3-trung-tam-dieu-phap-am-dieuphapam-net.mp3",
    "title" : "Phần 3 - Trung Tâm Diệu Pháp Âm - DieuPhapAm.Net",
    "children" : [ ]
  }, {
    "href" : "https://archive.org/download/d1c90dd56880eae608b15d7c022697f1/phan-4-trung-tam-dieu-phap-am-dieuphapam-net.mp3",
    "title" : "Phần 4 - Trung Tâm Diệu Pháp Âm - DieuPhapAm.Net",
    "children" : [ ]
  }, {
    "href" : "https://archive.org/download/d1c90dd56880eae608b15d7c022697f1/phan-5-trung-tam-dieu-phap-am-dieuphapam-net.mp3",
    "title" : "Phần 5 - Trung Tâm Diệu Pháp Âm - DieuPhapAm.Net",
    "children" : [ ]
  }, {
    "href" : "https://archive.org/download/d1c90dd56880eae608b15d7c022697f1/phan-6-trung-tam-dieu-phap-am-dieuphapam-net.mp3",
    "title" : "Phần 6 - Trung Tâm Diệu Pháp Âm - DieuPhapAm.Net",
    "children" : [ ]
  } ],
  "@context" : "https://readium.org/webpub-manifest/context.jsonld"
}