{
  "metadata" : {
    "identifier" : "https://www.nettruyenio.com/truyen-tranh/chi-no-wadachi-159700",
    "title" : "Chi no Wadachi - Chapter 1",
    "subtitle" : null,
    "author" : null,
    "narrator" : null,
    "language" : "vi",
    "description" : null,
    "publisher" : "N/A",
    "subject" : null,
    "modified" : null,
    "published" : "2023-08-06",
    "duration" : 0,
    "abridged" : false,
    "conformsTo" : "https://readium.org/webpub-manifest/profiles/divina",
    "numberOfPages" : 116,
    "readingProgression" : "ttb",
    "belongsTo" : null,
    "presentation" : {
      "fit" : "width",
      "overflow" : "scrolled",
      "continuous" : true
    },
    "@type" : null,
    "schema:license" : null
  },
  "links" : [ {
    "rel" : "self",
    "href" : "https://raw.githubusercontent.com/thuvienonline40/book_storage_collection/main/comic_manifest.json",
    "type" : "application/divina+json"
  } ],
  "readingOrder" : [ {
    "href" : "https://raw.githubusercontent.com/tsvhcomic29/comic_storage9/main/IMAGE/IMAGE_7d7bdd80160ebabc188c6376b1d7bc18_2568073366f0697d6879991d1a8ec287_44e1101912f8a5c8cc6ec93f60374648.jpg",
    "type" : "image/jpeg",
    "bitrate" : 0,
    "duration" : 0,
    "title" : null,
    "properties" : null,
    "alternate" : [ {
      "href" : "https://i441.ntcdntempv26.com/data/images/15970/316639/001-fix.jpg?data=net",
      "type" : "image/jpeg",
      "bitrate" : 0,
      "duration" : 0,
      "title" : null,
      "properties" : null,
      "alternate" : null
    } ]
  }, {
    "href" : "https://raw.githubusercontent.com/tsvhcomic29/comic_storage9/main/IMAGE/IMAGE_7d7bdd80160ebabc188c6376b1d7bc18_2568073366f0697d6879991d1a8ec287_8ffd0d5bf1e1f36e14ac0cf1778f9620.jpg",
    "type" : "image/jpeg",
    "bitrate" : 0,
    "duration" : 0,
    "title" : null,
    "properties" : null,
    "alternate" : [ {
      "href" : "https://i441.ntcdntempv26.com/data/images/15970/316639/002-fix.jpg?data=net",
      "type" : "image/jpeg",
      "bitrate" : 0,
      "duration" : 0,
      "title" : null,
      "properties" : null,
      "alternate" : null
    } ]
  }, {
    "href" : "https://raw.githubusercontent.com/tsvhcomic29/comic_storage9/main/IMAGE/IMAGE_7d7bdd80160ebabc188c6376b1d7bc18_2568073366f0697d6879991d1a8ec287_60ceca0aa8184a1008926ecefcf7e58d.jpg",
    "type" : "image/jpeg",
    "bitrate" : 0,
    "duration" : 0,
    "title" : null,
    "properties" : null,
    "alternate" : [ {
      "href" : "https://i441.ntcdntempv26.com/data/images/15970/316639/003-fix.jpg?data=net",
      "type" : "image/jpeg",
      "bitrate" : 0,
      "duration" : 0,
      "title" : null,
      "properties" : null,
      "alternate" : null
    } ]
  }, {
    "href" : "https://raw.githubusercontent.com/tsvhcomic29/comic_storage9/main/IMAGE/IMAGE_7d7bdd80160ebabc188c6376b1d7bc18_2568073366f0697d6879991d1a8ec287_dd4312a896988c7cb3c7f5f6fb39fb4f.jpg",
    "type" : "image/jpeg",
    "bitrate" : 0,
    "duration" : 0,
    "title" : null,
    "properties" : null,
    "alternate" : [ {
      "href" : "https://i441.ntcdntempv26.com/data/images/15970/316639/004-fix.jpg?data=net",
      "type" : "image/jpeg",
      "bitrate" : 0,
      "duration" : 0,
      "title" : null,
      "properties" : null,
      "alternate" : null
    } ]
  }, {
    "href" : "https://raw.githubusercontent.com/tsvhcomic29/comic_storage9/main/IMAGE/IMAGE_7d7bdd80160ebabc188c6376b1d7bc18_2568073366f0697d6879991d1a8ec287_2c5a86753baf3ca1597d2e1c1b11ff05.jpg",
    "type" : "image/jpeg",
    "bitrate" : 0,
    "duration" : 0,
    "title" : null,
    "properties" : null,
    "alternate" : [ {
      "href" : "https://i441.ntcdntempv26.com/data/images/15970/316639/005-fix.jpg?data=net",
      "type" : "image/jpeg",
      "bitrate" : 0,
      "duration" : 0,
      "title" : null,
      "properties" : null,
      "alternate" : null
    } ]
  }, {
    "href" : "https://raw.githubusercontent.com/tsvhcomic29/comic_storage9/main/IMAGE/IMAGE_7d7bdd80160ebabc188c6376b1d7bc18_2568073366f0697d6879991d1a8ec287_5dd7ba0b407c8567ddbb429c2bfc3d22.jpg",
    "type" : "image/jpeg",
    "bitrate" : 0,
    "duration" : 0,
    "title" : null,
    "properties" : null,
    "alternate" : [ {
      "href" : "https://i441.ntcdntempv26.com/data/images/15970/316639/006-fix.jpg?data=net",
      "type" : "image/jpeg",
      "bitrate" : 0,
      "duration" : 0,
      "title" : null,
      "properties" : null,
      "alternate" : null
    } ]
  }, {
    "href" : "https://raw.githubusercontent.com/tsvhcomic29/comic_storage9/main/IMAGE/IMAGE_7d7bdd80160ebabc188c6376b1d7bc18_2568073366f0697d6879991d1a8ec287_be70b6cbb0bf1959ad3a2e9f3bc3c55c.jpg",
    "type" : "image/jpeg",
    "bitrate" : 0,
    "duration" : 0,
    "title" : null,
    "properties" : null,
    "alternate" : [ {
      "href" : "https://i441.ntcdntempv26.com/data/images/15970/316639/007-fix.jpg?data=net",
      "type" : "image/jpeg",
      "bitrate" : 0,
      "duration" : 0,
      "title" : null,
      "properties" : null,
      "alternate" : null
    } ]
  }, {
    "href" : "https://raw.githubusercontent.com/tsvhcomic29/comic_storage9/main/IMAGE/IMAGE_7d7bdd80160ebabc188c6376b1d7bc18_2568073366f0697d6879991d1a8ec287_12a120aef0774bf3228f40adfb1dc837.jpg",
    "type" : "image/jpeg",
    "bitrate" : 0,
    "duration" : 0,
    "title" : null,
    "properties" : null,
    "alternate" : [ {
      "href" : "https://i441.ntcdntempv26.com/data/images/15970/316639/008-fix.jpg?data=net",
      "type" : "image/jpeg",
      "bitrate" : 0,
      "duration" : 0,
      "title" : null,
      "properties" : null,
      "alternate" : null
    } ]
  }, {
    "href" : "https://raw.githubusercontent.com/tsvhcomic29/comic_storage9/main/IMAGE/IMAGE_7d7bdd80160ebabc188c6376b1d7bc18_2568073366f0697d6879991d1a8ec287_111486763d0e3842faffe61d50a3f9da.jpg",
    "type" : "image/jpeg",
    "bitrate" : 0,
    "duration" : 0,
    "title" : null,
    "properties" : null,
    "alternate" : [ {
      "href" : "https://i441.ntcdntempv26.com/data/images/15970/316639/009-fix.jpg?data=net",
      "type" : "image/jpeg",
      "bitrate" : 0,
      "duration" : 0,
      "title" : null,
      "properties" : null,
      "alternate" : null
    } ]
  }, {
    "href" : "https://raw.githubusercontent.com/tsvhcomic29/comic_storage9/main/IMAGE/IMAGE_7d7bdd80160ebabc188c6376b1d7bc18_2568073366f0697d6879991d1a8ec287_30cae40adfd15c5a18f3ee399bc722c5.jpg",
    "type" : "image/jpeg",
    "bitrate" : 0,
    "duration" : 0,
    "title" : null,
    "properties" : null,
    "alternate" : [ {
      "href" : "https://i441.ntcdntempv26.com/data/images/15970/316639/010-fix.jpg?data=net",
      "type" : "image/jpeg",
      "bitrate" : 0,
      "duration" : 0,
      "title" : null,
      "properties" : null,
      "alternate" : null
    } ]
  }, {
    "href" : "https://raw.githubusercontent.com/tsvhcomic29/comic_storage9/main/IMAGE/IMAGE_7d7bdd80160ebabc188c6376b1d7bc18_2568073366f0697d6879991d1a8ec287_f9ac78168e5d4a489b06ef70fa743539.jpg",
    "type" : "image/jpeg",
    "bitrate" : 0,
    "duration" : 0,
    "title" : null,
    "properties" : null,
    "alternate" : [ {
      "href" : "https://i441.ntcdntempv26.com/data/images/15970/316639/011-fix.jpg?data=net",
      "type" : "image/jpeg",
      "bitrate" : 0,
      "duration" : 0,
      "title" : null,
      "properties" : null,
      "alternate" : null
    } ]
  }, {
    "href" : "https://raw.githubusercontent.com/tsvhcomic29/comic_storage9/main/IMAGE/IMAGE_7d7bdd80160ebabc188c6376b1d7bc18_2568073366f0697d6879991d1a8ec287_cfdda4f8ba2b329ee159dbe04bd67f41.jpg",
    "type" : "image/jpeg",
    "bitrate" : 0,
    "duration" : 0,
    "title" : null,
    "properties" : null,
    "alternate" : [ {
      "href" : "https://i441.ntcdntempv26.com/data/images/15970/316639/012-fix.jpg?data=net",
      "type" : "image/jpeg",
      "bitrate" : 0,
      "duration" : 0,
      "title" : null,
      "properties" : null,
      "alternate" : null
    } ]
  }, {
    "href" : "https://raw.githubusercontent.com/tsvhcomic29/comic_storage9/main/IMAGE/IMAGE_7d7bdd80160ebabc188c6376b1d7bc18_2568073366f0697d6879991d1a8ec287_fcd5162dabb753b7926316506927dc0e.jpg",
    "type" : "image/jpeg",
    "bitrate" : 0,
    "duration" : 0,
    "title" : null,
    "properties" : null,
    "alternate" : [ {
      "href" : "https://i441.ntcdntempv26.com/data/images/15970/316639/013-fix.jpg?data=net",
      "type" : "image/jpeg",
      "bitrate" : 0,
      "duration" : 0,
      "title" : null,
      "properties" : null,
      "alternate" : null
    } ]
  }, {
    "href" : "https://raw.githubusercontent.com/tsvhcomic29/comic_storage9/main/IMAGE/IMAGE_7d7bdd80160ebabc188c6376b1d7bc18_2568073366f0697d6879991d1a8ec287_b969d7a93f96e4015c182421af6c258f.jpg",
    "type" : "image/jpeg",
    "bitrate" : 0,
    "duration" : 0,
    "title" : null,
    "properties" : null,
    "alternate" : [ {
      "href" : "https://i441.ntcdntempv26.com/data/images/15970/316639/014-fix.jpg?data=net",
      "type" : "image/jpeg",
      "bitrate" : 0,
      "duration" : 0,
      "title" : null,
      "properties" : null,
      "alternate" : null
    } ]
  }, {
    "href" : "https://raw.githubusercontent.com/tsvhcomic29/comic_storage9/main/IMAGE/IMAGE_7d7bdd80160ebabc188c6376b1d7bc18_2568073366f0697d6879991d1a8ec287_9352f3904e20d235c803026da2994d28.jpg",
    "type" : "image/jpeg",
    "bitrate" : 0,
    "duration" : 0,
    "title" : null,
    "properties" : null,
    "alternate" : [ {
      "href" : "https://i441.ntcdntempv26.com/data/images/15970/316639/015-fix.jpg?data=net",
      "type" : "image/jpeg",
      "bitrate" : 0,
      "duration" : 0,
      "title" : null,
      "properties" : null,
      "alternate" : null
    } ]
  }, {
    "href" : "https://raw.githubusercontent.com/tsvhcomic29/comic_storage9/main/IMAGE/IMAGE_7d7bdd80160ebabc188c6376b1d7bc18_2568073366f0697d6879991d1a8ec287_ea8703ffe16a496333e0187a6db11514.jpg",
    "type" : "image/jpeg",
    "bitrate" : 0,
    "duration" : 0,
    "title" : null,
    "properties" : null,
    "alternate" : [ {
      "href" : "https://i441.ntcdntempv26.com/data/images/15970/316639/016-fix.jpg?data=net",
      "type" : "image/jpeg",
      "bitrate" : 0,
      "duration" : 0,
      "title" : null,
      "properties" : null,
      "alternate" : null
    } ]
  }, {
    "href" : "https://raw.githubusercontent.com/tsvhcomic29/comic_storage9/main/IMAGE/IMAGE_7d7bdd80160ebabc188c6376b1d7bc18_2568073366f0697d6879991d1a8ec287_97e2137f2a9bb39a32f87cc6ee10a2be.jpg",
    "type" : "image/jpeg",
    "bitrate" : 0,
    "duration" : 0,
    "title" : null,
    "properties" : null,
    "alternate" : [ {
      "href" : "https://i441.ntcdntempv26.com/data/images/15970/316639/017-fix.jpg?data=net",
      "type" : "image/jpeg",
      "bitrate" : 0,
      "duration" : 0,
      "title" : null,
      "properties" : null,
      "alternate" : null
    } ]
  }, {
    "href" : "https://raw.githubusercontent.com/tsvhcomic29/comic_storage9/main/IMAGE/IMAGE_7d7bdd80160ebabc188c6376b1d7bc18_2568073366f0697d6879991d1a8ec287_0223a2de72341ffe22b1287bee5ac98b.jpg",
    "type" : "image/jpeg",
    "bitrate" : 0,
    "duration" : 0,
    "title" : null,
    "properties" : null,
    "alternate" : [ {
      "href" : "https://i441.ntcdntempv26.com/data/images/15970/316639/018-fix.jpg?data=net",
      "type" : "image/jpeg",
      "bitrate" : 0,
      "duration" : 0,
      "title" : null,
      "properties" : null,
      "alternate" : null
    } ]
  }, {
    "href" : "https://raw.githubusercontent.com/tsvhcomic29/comic_storage9/main/IMAGE/IMAGE_7d7bdd80160ebabc188c6376b1d7bc18_2568073366f0697d6879991d1a8ec287_af2748ba1794fda0d1e809bedc276ccb.jpg",
    "type" : "image/jpeg",
    "bitrate" : 0,
    "duration" : 0,
    "title" : null,
    "properties" : null,
    "alternate" : [ {
      "href" : "https://i441.ntcdntempv26.com/data/images/15970/316639/019-fix.jpg?data=net",
      "type" : "image/jpeg",
      "bitrate" : 0,
      "duration" : 0,
      "title" : null,
      "properties" : null,
      "alternate" : null
    } ]
  }, {
    "href" : "https://raw.githubusercontent.com/tsvhcomic29/comic_storage9/main/IMAGE/IMAGE_7d7bdd80160ebabc188c6376b1d7bc18_2568073366f0697d6879991d1a8ec287_cd3883e9f52f23fc00a81ef2c57e88df.jpg",
    "type" : "image/jpeg",
    "bitrate" : 0,
    "duration" : 0,
    "title" : null,
    "properties" : null,
    "alternate" : [ {
      "href" : "https://i441.ntcdntempv26.com/data/images/15970/316639/020-fix.jpg?data=net",
      "type" : "image/jpeg",
      "bitrate" : 0,
      "duration" : 0,
      "title" : null,
      "properties" : null,
      "alternate" : null
    } ]
  }, {
    "href" : "https://raw.githubusercontent.com/tsvhcomic29/comic_storage9/main/IMAGE/IMAGE_7d7bdd80160ebabc188c6376b1d7bc18_2568073366f0697d6879991d1a8ec287_f832fc178fbbfdfbbe2232cf7ef2340f.jpg",
    "type" : "image/jpeg",
    "bitrate" : 0,
    "duration" : 0,
    "title" : null,
    "properties" : null,
    "alternate" : [ {
      "href" : "https://i441.ntcdntempv26.com/data/images/15970/316639/021-fix.jpg?data=net",
      "type" : "image/jpeg",
      "bitrate" : 0,
      "duration" : 0,
      "title" : null,
      "properties" : null,
      "alternate" : null
    } ]
  }, {
    "href" : "https://raw.githubusercontent.com/tsvhcomic29/comic_storage9/main/IMAGE/IMAGE_7d7bdd80160ebabc188c6376b1d7bc18_2568073366f0697d6879991d1a8ec287_b033eba8364b9363abad3f926122aab6.jpg",
    "type" : "image/jpeg",
    "bitrate" : 0,
    "duration" : 0,
    "title" : null,
    "properties" : null,
    "alternate" : [ {
      "href" : "https://i441.ntcdntempv26.com/data/images/15970/316639/022-fix.jpg?data=net",
      "type" : "image/jpeg",
      "bitrate" : 0,
      "duration" : 0,
      "title" : null,
      "properties" : null,
      "alternate" : null
    } ]
  }, {
    "href" : "https://raw.githubusercontent.com/tsvhcomic29/comic_storage9/main/IMAGE/IMAGE_7d7bdd80160ebabc188c6376b1d7bc18_2568073366f0697d6879991d1a8ec287_a3917ba1b5310f7aa037844f14e861bf.jpg",
    "type" : "image/jpeg",
    "bitrate" : 0,
    "duration" : 0,
    "title" : null,
    "properties" : null,
    "alternate" : [ {
      "href" : "https://i441.ntcdntempv26.com/data/images/15970/316639/023-fix.jpg?data=net",
      "type" : "image/jpeg",
      "bitrate" : 0,
      "duration" : 0,
      "title" : null,
      "properties" : null,
      "alternate" : null
    } ]
  }, {
    "href" : "https://raw.githubusercontent.com/tsvhcomic29/comic_storage9/main/IMAGE/IMAGE_7d7bdd80160ebabc188c6376b1d7bc18_2568073366f0697d6879991d1a8ec287_7b380485fd313231ded1e634b1554e47.jpg",
    "type" : "image/jpeg",
    "bitrate" : 0,
    "duration" : 0,
    "title" : null,
    "properties" : null,
    "alternate" : [ {
      "href" : "https://i441.ntcdntempv26.com/data/images/15970/316639/024-fix.jpg?data=net",
      "type" : "image/jpeg",
      "bitrate" : 0,
      "duration" : 0,
      "title" : null,
      "properties" : null,
      "alternate" : null
    } ]
  }, {
    "href" : "https://raw.githubusercontent.com/tsvhcomic29/comic_storage9/main/IMAGE/IMAGE_7d7bdd80160ebabc188c6376b1d7bc18_2568073366f0697d6879991d1a8ec287_0cdfb0bfaa5a7404637d15aee47d741c.jpg",
    "type" : "image/jpeg",
    "bitrate" : 0,
    "duration" : 0,
    "title" : null,
    "properties" : null,
    "alternate" : [ {
      "href" : "https://i441.ntcdntempv26.com/data/images/15970/316639/025-fix.jpg?data=net",
      "type" : "image/jpeg",
      "bitrate" : 0,
      "duration" : 0,
      "title" : null,
      "properties" : null,
      "alternate" : null
    } ]
  }, {
    "href" : "https://raw.githubusercontent.com/tsvhcomic29/comic_storage9/main/IMAGE/IMAGE_7d7bdd80160ebabc188c6376b1d7bc18_2568073366f0697d6879991d1a8ec287_3298a89333fad9df03d53f825197c6a8.jpg",
    "type" : "image/jpeg",
    "bitrate" : 0,
    "duration" : 0,
    "title" : null,
    "properties" : null,
    "alternate" : [ {
      "href" : "https://i441.ntcdntempv26.com/data/images/15970/316639/026-fix.jpg?data=net",
      "type" : "image/jpeg",
      "bitrate" : 0,
      "duration" : 0,
      "title" : null,
      "properties" : null,
      "alternate" : null
    } ]
  }, {
    "href" : "https://raw.githubusercontent.com/tsvhcomic29/comic_storage9/main/IMAGE/IMAGE_7d7bdd80160ebabc188c6376b1d7bc18_2568073366f0697d6879991d1a8ec287_b60e04adc6f3d649b4c3d47e0b8782fe.jpg",
    "type" : "image/jpeg",
    "bitrate" : 0,
    "duration" : 0,
    "title" : null,
    "properties" : null,
    "alternate" : [ {
      "href" : "https://i441.ntcdntempv26.com/data/images/15970/316639/027-fix.jpg?data=net",
      "type" : "image/jpeg",
      "bitrate" : 0,
      "duration" : 0,
      "title" : null,
      "properties" : null,
      "alternate" : null
    } ]
  }, {
    "href" : "https://raw.githubusercontent.com/tsvhcomic29/comic_storage9/main/IMAGE/IMAGE_7d7bdd80160ebabc188c6376b1d7bc18_2568073366f0697d6879991d1a8ec287_ccf6927b8a03f13ec191efb41c3b4e41.jpg",
    "type" : "image/jpeg",
    "bitrate" : 0,
    "duration" : 0,
    "title" : null,
    "properties" : null,
    "alternate" : [ {
      "href" : "https://i441.ntcdntempv26.com/data/images/15970/316639/028-fix.jpg?data=net",
      "type" : "image/jpeg",
      "bitrate" : 0,
      "duration" : 0,
      "title" : null,
      "properties" : null,
      "alternate" : null
    } ]
  }, {
    "href" : "https://raw.githubusercontent.com/tsvhcomic29/comic_storage9/main/IMAGE/IMAGE_7d7bdd80160ebabc188c6376b1d7bc18_2568073366f0697d6879991d1a8ec287_2d4eb0144e5922072f736086dfa4886f.jpg",
    "type" : "image/jpeg",
    "bitrate" : 0,
    "duration" : 0,
    "title" : null,
    "properties" : null,
    "alternate" : [ {
      "href" : "https://i441.ntcdntempv26.com/data/images/15970/316639/029-fix.jpg?data=net",
      "type" : "image/jpeg",
      "bitrate" : 0,
      "duration" : 0,
      "title" : null,
      "properties" : null,
      "alternate" : null
    } ]
  }, {
    "href" : "https://raw.githubusercontent.com/tsvhcomic29/comic_storage9/main/IMAGE/IMAGE_7d7bdd80160ebabc188c6376b1d7bc18_2568073366f0697d6879991d1a8ec287_8fe248776f8587c96dedd905e73a3fde.jpg",
    "type" : "image/jpeg",
    "bitrate" : 0,
    "duration" : 0,
    "title" : null,
    "properties" : null,
    "alternate" : [ {
      "href" : "https://i441.ntcdntempv26.com/data/images/15970/316639/030-fix.jpg?data=net",
      "type" : "image/jpeg",
      "bitrate" : 0,
      "duration" : 0,
      "title" : null,
      "properties" : null,
      "alternate" : null
    } ]
  }, {
    "href" : "https://raw.githubusercontent.com/tsvhcomic29/comic_storage9/main/IMAGE/IMAGE_7d7bdd80160ebabc188c6376b1d7bc18_2568073366f0697d6879991d1a8ec287_ca49093de4ceae12261da0c3f062af1f.jpg",
    "type" : "image/jpeg",
    "bitrate" : 0,
    "duration" : 0,
    "title" : null,
    "properties" : null,
    "alternate" : [ {
      "href" : "https://i441.ntcdntempv26.com/data/images/15970/316639/031-fix.jpg?data=net",
      "type" : "image/jpeg",
      "bitrate" : 0,
      "duration" : 0,
      "title" : null,
      "properties" : null,
      "alternate" : null
    } ]
  }, {
    "href" : "https://raw.githubusercontent.com/tsvhcomic29/comic_storage9/main/IMAGE/IMAGE_7d7bdd80160ebabc188c6376b1d7bc18_2568073366f0697d6879991d1a8ec287_343a3ca250b8d013fe3cadb4f9a794d6.jpg",
    "type" : "image/jpeg",
    "bitrate" : 0,
    "duration" : 0,
    "title" : null,
    "properties" : null,
    "alternate" : [ {
      "href" : "https://i441.ntcdntempv26.com/data/images/15970/316639/032-fix.jpg?data=net",
      "type" : "image/jpeg",
      "bitrate" : 0,
      "duration" : 0,
      "title" : null,
      "properties" : null,
      "alternate" : null
    } ]
  }, {
    "href" : "https://raw.githubusercontent.com/tsvhcomic29/comic_storage9/main/IMAGE/IMAGE_7d7bdd80160ebabc188c6376b1d7bc18_2568073366f0697d6879991d1a8ec287_cba579f63ff7ce90a8c1cc40ce4821b8.jpg",
    "type" : "image/jpeg",
    "bitrate" : 0,
    "duration" : 0,
    "title" : null,
    "properties" : null,
    "alternate" : [ {
      "href" : "https://i441.ntcdntempv26.com/data/images/15970/316639/033-fix.jpg?data=net",
      "type" : "image/jpeg",
      "bitrate" : 0,
      "duration" : 0,
      "title" : null,
      "properties" : null,
      "alternate" : null
    } ]
  }, {
    "href" : "https://raw.githubusercontent.com/tsvhcomic29/comic_storage9/main/IMAGE/IMAGE_7d7bdd80160ebabc188c6376b1d7bc18_2568073366f0697d6879991d1a8ec287_d355d98926c89ad18273fec302056b2a.jpg",
    "type" : "image/jpeg",
    "bitrate" : 0,
    "duration" : 0,
    "title" : null,
    "properties" : null,
    "alternate" : [ {
      "href" : "https://i441.ntcdntempv26.com/data/images/15970/316639/034-fix.jpg?data=net",
      "type" : "image/jpeg",
      "bitrate" : 0,
      "duration" : 0,
      "title" : null,
      "properties" : null,
      "alternate" : null
    } ]
  }, {
    "href" : "https://raw.githubusercontent.com/tsvhcomic29/comic_storage9/main/IMAGE/IMAGE_7d7bdd80160ebabc188c6376b1d7bc18_2568073366f0697d6879991d1a8ec287_9e51d39adc85b82101c7c4085a53383d.jpg",
    "type" : "image/jpeg",
    "bitrate" : 0,
    "duration" : 0,
    "title" : null,
    "properties" : null,
    "alternate" : [ {
      "href" : "https://i441.ntcdntempv26.com/data/images/15970/316639/035-fix.jpg?data=net",
      "type" : "image/jpeg",
      "bitrate" : 0,
      "duration" : 0,
      "title" : null,
      "properties" : null,
      "alternate" : null
    } ]
  }, {
    "href" : "https://raw.githubusercontent.com/tsvhcomic29/comic_storage9/main/IMAGE/IMAGE_7d7bdd80160ebabc188c6376b1d7bc18_2568073366f0697d6879991d1a8ec287_e4aee13e98a8db0f1221ffa9eca6a81b.jpg",
    "type" : "image/jpeg",
    "bitrate" : 0,
    "duration" : 0,
    "title" : null,
    "properties" : null,
    "alternate" : [ {
      "href" : "https://i441.ntcdntempv26.com/data/images/15970/316639/036-fix.jpg?data=net",
      "type" : "image/jpeg",
      "bitrate" : 0,
      "duration" : 0,
      "title" : null,
      "properties" : null,
      "alternate" : null
    } ]
  }, {
    "href" : "https://raw.githubusercontent.com/tsvhcomic29/comic_storage9/main/IMAGE/IMAGE_7d7bdd80160ebabc188c6376b1d7bc18_2568073366f0697d6879991d1a8ec287_fa6b7691e58e8c630f6b35fe8267d8ad.jpg",
    "type" : "image/jpeg",
    "bitrate" : 0,
    "duration" : 0,
    "title" : null,
    "properties" : null,
    "alternate" : [ {
      "href" : "https://i441.ntcdntempv26.com/data/images/15970/316639/037-fix.jpg?data=net",
      "type" : "image/jpeg",
      "bitrate" : 0,
      "duration" : 0,
      "title" : null,
      "properties" : null,
      "alternate" : null
    } ]
  }, {
    "href" : "https://raw.githubusercontent.com/tsvhcomic29/comic_storage9/main/IMAGE/IMAGE_7d7bdd80160ebabc188c6376b1d7bc18_2568073366f0697d6879991d1a8ec287_e2f5c7748c5687d3288c485c3637ee20.jpg",
    "type" : "image/jpeg",
    "bitrate" : 0,
    "duration" : 0,
    "title" : null,
    "properties" : null,
    "alternate" : [ {
      "href" : "https://i441.ntcdntempv26.com/data/images/15970/316639/038-fix.jpg?data=net",
      "type" : "image/jpeg",
      "bitrate" : 0,
      "duration" : 0,
      "title" : null,
      "properties" : null,
      "alternate" : null
    } ]
  }, {
    "href" : "https://raw.githubusercontent.com/tsvhcomic29/comic_storage9/main/IMAGE/IMAGE_7d7bdd80160ebabc188c6376b1d7bc18_2568073366f0697d6879991d1a8ec287_25957dc089dc367e2c92e5ae352df88b.jpg",
    "type" : "image/jpeg",
    "bitrate" : 0,
    "duration" : 0,
    "title" : null,
    "properties" : null,
    "alternate" : [ {
      "href" : "https://i441.ntcdntempv26.com/data/images/15970/316639/039-fix.jpg?data=net",
      "type" : "image/jpeg",
      "bitrate" : 0,
      "duration" : 0,
      "title" : null,
      "properties" : null,
      "alternate" : null
    } ]
  }, {
    "href" : "https://raw.githubusercontent.com/tsvhcomic29/comic_storage9/main/IMAGE/IMAGE_7d7bdd80160ebabc188c6376b1d7bc18_2568073366f0697d6879991d1a8ec287_48bd818aad94108b28f6408d2a8658ae.jpg",
    "type" : "image/jpeg",
    "bitrate" : 0,
    "duration" : 0,
    "title" : null,
    "properties" : null,
    "alternate" : [ {
      "href" : "https://i441.ntcdntempv26.com/data/images/15970/316639/040-fix.jpg?data=net",
      "type" : "image/jpeg",
      "bitrate" : 0,
      "duration" : 0,
      "title" : null,
      "properties" : null,
      "alternate" : null
    } ]
  }, {
    "href" : "https://raw.githubusercontent.com/tsvhcomic29/comic_storage9/main/IMAGE/IMAGE_7d7bdd80160ebabc188c6376b1d7bc18_2568073366f0697d6879991d1a8ec287_78b54efc1ffbe05c098990f2966b4392.jpg",
    "type" : "image/jpeg",
    "bitrate" : 0,
    "duration" : 0,
    "title" : null,
    "properties" : null,
    "alternate" : [ {
      "href" : "https://i441.ntcdntempv26.com/data/images/15970/316639/041-fix.jpg?data=net",
      "type" : "image/jpeg",
      "bitrate" : 0,
      "duration" : 0,
      "title" : null,
      "properties" : null,
      "alternate" : null
    } ]
  }, {
    "href" : "https://raw.githubusercontent.com/tsvhcomic29/comic_storage9/main/IMAGE/IMAGE_7d7bdd80160ebabc188c6376b1d7bc18_2568073366f0697d6879991d1a8ec287_1e2a163e058064607c776b0379e868a0.jpg",
    "type" : "image/jpeg",
    "bitrate" : 0,
    "duration" : 0,
    "title" : null,
    "properties" : null,
    "alternate" : [ {
      "href" : "https://i441.ntcdntempv26.com/data/images/15970/316639/042-fix.jpg?data=net",
      "type" : "image/jpeg",
      "bitrate" : 0,
      "duration" : 0,
      "title" : null,
      "properties" : null,
      "alternate" : null
    } ]
  }, {
    "href" : "https://raw.githubusercontent.com/tsvhcomic29/comic_storage9/main/IMAGE/IMAGE_7d7bdd80160ebabc188c6376b1d7bc18_2568073366f0697d6879991d1a8ec287_952d40d685ceb5c597cbc32040a9036c.jpg",
    "type" : "image/jpeg",
    "bitrate" : 0,
    "duration" : 0,
    "title" : null,
    "properties" : null,
    "alternate" : [ {
      "href" : "https://i441.ntcdntempv26.com/data/images/15970/316639/043-fix.jpg?data=net",
      "type" : "image/jpeg",
      "bitrate" : 0,
      "duration" : 0,
      "title" : null,
      "properties" : null,
      "alternate" : null
    } ]
  }, {
    "href" : "https://raw.githubusercontent.com/tsvhcomic29/comic_storage9/main/IMAGE/IMAGE_7d7bdd80160ebabc188c6376b1d7bc18_2568073366f0697d6879991d1a8ec287_1defc2f14f7f53e85c57dd2649fb1dfd.jpg",
    "type" : "image/jpeg",
    "bitrate" : 0,
    "duration" : 0,
    "title" : null,
    "properties" : null,
    "alternate" : [ {
      "href" : "https://i441.ntcdntempv26.com/data/images/15970/316639/044-fix.jpg?data=net",
      "type" : "image/jpeg",
      "bitrate" : 0,
      "duration" : 0,
      "title" : null,
      "properties" : null,
      "alternate" : null
    } ]
  }, {
    "href" : "https://raw.githubusercontent.com/tsvhcomic29/comic_storage9/main/IMAGE/IMAGE_7d7bdd80160ebabc188c6376b1d7bc18_2568073366f0697d6879991d1a8ec287_19ca05e745235d3f4f7e77701f7521c4.jpg",
    "type" : "image/jpeg",
    "bitrate" : 0,
    "duration" : 0,
    "title" : null,
    "properties" : null,
    "alternate" : [ {
      "href" : "https://i441.ntcdntempv26.com/data/images/15970/316639/045-fix.jpg?data=net",
      "type" : "image/jpeg",
      "bitrate" : 0,
      "duration" : 0,
      "title" : null,
      "properties" : null,
      "alternate" : null
    } ]
  }, {
    "href" : "https://raw.githubusercontent.com/tsvhcomic29/comic_storage9/main/IMAGE/IMAGE_7d7bdd80160ebabc188c6376b1d7bc18_2568073366f0697d6879991d1a8ec287_fd9f52e7642a25e5e35876bf34bb3217.jpg",
    "type" : "image/jpeg",
    "bitrate" : 0,
    "duration" : 0,
    "title" : null,
    "properties" : null,
    "alternate" : [ {
      "href" : "https://i441.ntcdntempv26.com/data/images/15970/316639/046-fix.jpg?data=net",
      "type" : "image/jpeg",
      "bitrate" : 0,
      "duration" : 0,
      "title" : null,
      "properties" : null,
      "alternate" : null
    } ]
  }, {
    "href" : "https://raw.githubusercontent.com/tsvhcomic29/comic_storage9/main/IMAGE/IMAGE_7d7bdd80160ebabc188c6376b1d7bc18_2568073366f0697d6879991d1a8ec287_1d019de61383ed1ffa63dd987fff85da.jpg",
    "type" : "image/jpeg",
    "bitrate" : 0,
    "duration" : 0,
    "title" : null,
    "properties" : null,
    "alternate" : [ {
      "href" : "https://i441.ntcdntempv26.com/data/images/15970/316639/047-fix.jpg?data=net",
      "type" : "image/jpeg",
      "bitrate" : 0,
      "duration" : 0,
      "title" : null,
      "properties" : null,
      "alternate" : null
    } ]
  }, {
    "href" : "https://raw.githubusercontent.com/tsvhcomic29/comic_storage9/main/IMAGE/IMAGE_7d7bdd80160ebabc188c6376b1d7bc18_2568073366f0697d6879991d1a8ec287_9e734b1b53aa7a5012421bada176f0f3.jpg",
    "type" : "image/jpeg",
    "bitrate" : 0,
    "duration" : 0,
    "title" : null,
    "properties" : null,
    "alternate" : [ {
      "href" : "https://i441.ntcdntempv26.com/data/images/15970/316639/048-fix.jpg?data=net",
      "type" : "image/jpeg",
      "bitrate" : 0,
      "duration" : 0,
      "title" : null,
      "properties" : null,
      "alternate" : null
    } ]
  } ],
  "toc" : null,
  "@context" : "https://readium.org/webpub-manifest/context.jsonld"
}